dot_access/__init__.py
dot_access-0.0.1.dist-info/DESCRIPTION.rst
dot_access-0.0.1.dist-info/METADATA
dot_access-0.0.1.dist-info/RECORD
dot_access-0.0.1.dist-info/WHEEL
dot_access-0.0.1.dist-info/metadata.json
dot_access-0.0.1.dist-info/top_level.txt
tests/__init__.py
tests/all_test.py
